xrprimer_cpp.cpython-310-x86_64-linux-gnu.so
xrprimer/__init__.py
xrprimer/version.py
xrprimer/data_structure/limbs.py
xrprimer/data_structure/__init__.py
xrprimer/data_structure/keypoints.py
xrprimer/data_structure/camera/camera.py
xrprimer/data_structure/camera/__init__.py
xrprimer/data_structure/camera/fisheye_camera.py
xrprimer/data_structure/camera/pinhole_camera.py
xrprimer/data_structure/camera/omni_camera.py
xrprimer/visualization/__init__.py
xrprimer/visualization/palette/__init__.py
xrprimer/visualization/palette/line_palette.py
xrprimer/visualization/palette/point_palette.py
xrprimer/visualization/presets/__init__.py
xrprimer/visualization/presets/axis.py
xrprimer/visualization/opencv/__init__.py
xrprimer/visualization/opencv/plot_frame.py
xrprimer/visualization/opencv/plot_video.py
xrprimer/visualization/matplotlib/__init__.py
xrprimer/visualization/matplotlib/plot_frame.py
xrprimer/visualization/matplotlib/plot_video.py
xrprimer/visualization/keypoints/visualize_keypoints3d.py
xrprimer/visualization/keypoints/__init__.py
xrprimer/visualization/keypoints/visualize_keypoints2d.py
xrprimer/ops/__init__.py
xrprimer/ops/projection/builder.py
xrprimer/ops/projection/opencv_projector.py
xrprimer/ops/projection/__init__.py
xrprimer/ops/projection/base_projector.py
xrprimer/ops/triangulation/builder.py
xrprimer/ops/triangulation/__init__.py
xrprimer/ops/triangulation/opencv_triangulator.py
xrprimer/ops/triangulation/base_triangulator.py
xrprimer/calibration/builder.py
xrprimer/calibration/__init__.py
xrprimer/calibration/mview_pinhole_calibrator.py
xrprimer/calibration/sview_fisheye_calibrator.py
xrprimer/calibration/base_calibrator.py
xrprimer/calibration/mview_fisheye_calibrator.py
xrprimer/utils/__init__.py
xrprimer/utils/path_utils.py
xrprimer/utils/ffmpeg_utils.py
xrprimer/utils/log_utils.py
xrprimer/utils/visualization_utils.py
xrprimer/utils/synbody_utils.py
xrprimer/transform/__init__.py
xrprimer-0.7.1.dist-info/RECORD
xrprimer-0.7.1.dist-info/WHEEL
xrprimer-0.7.1.dist-info/LICENSE
xrprimer-0.7.1.dist-info/METADATA
xrprimer-0.7.1.dist-info/top_level.txt
