Metadata-Version: 2.1
Name: xrprimer
Version: 0.7.1
Summary: description
Author: OpenXRLab
Author-email: openxrlab@pjlab.org.cn
License: Apache License 2.0
Project-URL: Documentation, https://xrprimer.readthedocs.io/en/latest/
Project-URL: Source, https://github.com/openxrlab/xrprimer/
Keywords: xrprimer
Classifier: Development Status :: 4 - Beta
Classifier: License :: OSI Approved :: Apache Software License
Classifier: Operating System :: OS Independent
Classifier: Programming Language :: Python :: 3
Classifier: Programming Language :: Python :: 3.6
Classifier: Programming Language :: Python :: 3.7
Classifier: Programming Language :: Python :: 3.8
Classifier: Programming Language :: Python :: 3.9
Classifier: Programming Language :: Python :: 3.10
Requires-Python: >=3.6, <3.11
License-File: LICENSE
Requires-Dist: numpy
